arkcclient-0.3.1.dist-info/metadata.json
arkcclient-0.3.1.dist-info/DESCRIPTION.rst
arkcclient-0.3.1.dist-info/entry_points.txt
arkcclient-0.3.1.dist-info/top_level.txt
arkcclient-0.3.1.dist-info/RECORD
arkcclient-0.3.1.dist-info/WHEEL
arkcclient-0.3.1.dist-info/METADATA
arkcclient/client.py
arkcclient/common.py
arkcclient/meekclient.py
arkcclient/main.py
arkcclient/ptclient.py
arkcclient/coordinator.py
arkcclient/server.py
arkcclient/__init__.py
arkcclient/pyotp/totp.py
arkcclient/pyotp/utils.py
arkcclient/pyotp/LICENSE
arkcclient/pyotp/otp.py
arkcclient/pyotp/__init__.py
